<?xml version='1.0' encoding='UTF-8'?><findItemsByKeywordsResponse xmlns="http://www.ebay.com/marketplace/search/v1/services"><ack>Success</ack><version>1.13.0</version><timestamp>2016-01-05T05:04:07.637Z</timestamp><searchResult count="10"><item><itemId>272089505055</itemId><title>Star Wars The Black Series! Luke Skywalker! Hasbro 3.75-Inch Action Figure!</title><globalId>EBAY-US</globalId><primaryCategory><categoryId>75708</categoryId><categoryName>TV, Movie &amp; Video Games</categoryName></primaryCategory><galleryURL>http://thumbs4.ebaystatic.com/m/mo6BrvNXORpOX1rG6r1c9Qg/140.jpg</galleryURL><viewItemURL>http://www.ebay.com/itm/Star-Wars-Black-Series-Luke-Skywalker-Hasbro-3-75-Inch-Action-Figure-/272089505055</viewItemURL><paymentMethod>PayPal</paymentMethod><autoPay>false</autoPay><postalCode>85249</postalCode><location>Chandler,AZ,USA</location><country>US</country><shippingInfo><shippingServiceCost currencyId="USD">4.0</shippingServiceCost><shippingType>FlatDomesticCalculatedInternational</shippingType><shipToLocations>US</shipToLocations><shipToLocations>CA</shipToLocations><shipToLocations>GB</shipToLocations><shipToLocations>AU</shipToLocations><shipToLocations>AT</shipToLocations><shipToLocations>BE</shipToLocations><shipToLocations>FR</shipToLocations><shipToLocations>DE</shipToLocations><shipToLocations>IT</shipToLocations><shipToLocations>JP</shipToLocations><shipToLocations>ES</shipToLocations><shipToLocations>TW</shipToLocations><shipToLocations>NL</shipToLocations><shipToLocations>CN</shipToLocations><shipToLocations>HK</shipToLocations><shipToLocations>MX</shipToLocations><shipToLocations>DK</shipToLocations><shipToLocations>RO</shipToLocations><shipToLocations>SK</shipToLocations><shipToLocations>BG</shipToLocations><shipToLocations>CZ</shipToLocations><shipToLocations>FI</shipToLocations><shipToLocations>HU</shipToLocations><shipToLocations>LV</shipToLocations><shipToLocations>LT</shipToLocations><shipToLocations>MT</shipToLocations><shipToLocations>EE</shipToLocations><shipToLocations>GR</shipToLocations><shipToLocations>PT</shipToLocations><shipToLocations>CY</shipToLocations><shipToLocations>SI</shipToLocations><shipToLocations>SE</shipToLocations><shipToLocations>KR</shipToLocations><shipToLocations>ID</shipToLocations><shipToLocations>ZA</shipToLocations><shipToLocations>TH</shipToLocations><shipToLocations>IE</shipToLocations><shipToLocations>PL</shipToLocations><shipToLocations>RU</shipToLocations><shipToLocations>IL</shipToLocations><expeditedShipping>false</expeditedShipping><oneDayShippingAvailable>false</oneDayShippingAvailable><handlingTime>1</handlingTime></shippingInfo><sellingStatus><currentPrice currencyId="USD">20.99</currentPrice><convertedCurrentPrice currencyId="USD">20.99</convertedCurrentPrice><sellingState>Active</sellingState><timeLeft>P23DT0H52M7S</timeLeft></sellingStatus><listingInfo><bestOfferEnabled>false</bestOfferEnabled><buyItNowAvailable>false</buyItNowAvailable><startTime>2015-12-29T05:56:14.000Z</startTime><endTime>2016-01-28T05:56:14.000Z</endTime><listingType>StoreInventory</listingType><gift>false</gift></listingInfo><returnsAccepted>true</returnsAccepted><condition><conditionId>1000</conditionId><conditionDisplayName>New</conditionDisplayName></condition><isMultiVariationListing>false</isMultiVariationListing><topRatedListing>true</topRatedListing></item><item><itemId>221932209195</itemId><title>Star Wars The Force Awakens 3.75-Inch Vehicle Poe Dameron's X-Wing</title><globalId>EBAY-US</globalId><subtitle>Buy direct from HasbroToyShop</subtitle><primaryCategory><categoryId>75708</categoryId><categoryName>TV, Movie &amp; Video Games</categoryName></primaryCategory><galleryURL>http://thumbs4.ebaystatic.com/m/ma0h0dw1m7LYIORYNlkyKlg/140.jpg</galleryURL><viewItemURL>http://www.ebay.com/itm/Star-Wars-Force-Awakens-3-75-Inch-Vehicle-Poe-Damerons-X-Wing-/221932209195</viewItemURL><paymentMethod>PayPal</paymentMethod><autoPay>true</autoPay><location>USA</location><country>US</country><shippingInfo><shippingServiceCost currencyId="USD">0.0</shippingServiceCost><shippingType>Free</shippingType><shipToLocations>US</shipToLocations><expeditedShipping>true</expeditedShipping><oneDayShippingAvailable>true</oneDayShippingAvailable><handlingTime>2</handlingTime></shippingInfo><sellingStatus><currentPrice currencyId="USD">39.99</currentPrice><convertedCurrentPrice currencyId="USD">39.99</convertedCurrentPrice><sellingState>Active</sellingState><timeLeft>P28DT16H7M2S</timeLeft></sellingStatus><listingInfo><bestOfferEnabled>false</bestOfferEnabled><buyItNowAvailable>false</buyItNowAvailable><startTime>2015-11-04T21:06:09.000Z</startTime><endTime>2016-02-02T21:11:09.000Z</endTime><listingType>FixedPrice</listingType><gift>false</gift></listingInfo><returnsAccepted>true</returnsAccepted><condition><conditionId>1000</conditionId><conditionDisplayName>New</conditionDisplayName></condition><isMultiVariationListing>false</isMultiVariationListing><discountPriceInfo><originalRetailPrice currencyId="USD">49.99</originalRetailPrice><pricingTreatment>STP</pricingTreatment><soldOnEbay>true</soldOnEbay><soldOffEbay>false</soldOffEbay></discountPriceInfo><topRatedListing>false</topRatedListing></item><item><itemId>252136827922</itemId><title>Star Wars Hasbro Action Figure 6 inches Black Force Series 2 DARTH VADER NIB </title><globalId>EBAY-US</globalId><primaryCategory><categoryId>75708</categoryId><categoryName>TV, Movie &amp; Video Games</categoryName></primaryCategory><galleryURL>http://thumbs3.ebaystatic.com/m/mxNLD0g08z9SipBTiuSOkSg/140.jpg</galleryURL><viewItemURL>http://www.ebay.com/itm/Star-Wars-Hasbro-Action-Figure-6-inches-Black-Force-Series-2-DARTH-VADER-NIB-/252136827922</viewItemURL><paymentMethod>PayPal</paymentMethod><autoPay>true</autoPay><postalCode>90210</postalCode><location>Beverly Hills,CA,USA</location><country>US</country><shippingInfo><shippingServiceCost currencyId="USD">0.0</shippingServiceCost><shippingType>Free</shippingType><shipToLocations>US</shipToLocations><expeditedShipping>false</expeditedShipping><oneDayShippingAvailable>false</oneDayShippingAvailable><handlingTime>2</handlingTime></shippingInfo><sellingStatus><currentPrice currencyId="USD">37.99</currentPrice><convertedCurrentPrice currencyId="USD">37.99</convertedCurrentPrice><sellingState>Active</sellingState><timeLeft>P15DT10H46M21S</timeLeft></sellingStatus><listingInfo><bestOfferEnabled>false</bestOfferEnabled><buyItNowAvailable>false</buyItNowAvailable><startTime>2015-10-22T15:45:28.000Z</startTime><endTime>2016-01-20T15:50:28.000Z</endTime><listingType>StoreInventory</listingType><gift>false</gift></listingInfo><returnsAccepted>true</returnsAccepted><condition><conditionId>1000</conditionId><conditionDisplayName>New</conditionDisplayName></condition><isMultiVariationListing>false</isMultiVariationListing><topRatedListing>false</topRatedListing></item><item><itemId>321573499601</itemId><title>Star Wars The Black Series Luke Skywalker Figure by Hasbro</title><globalId>EBAY-US</globalId><subtitle>Buy direct from HasbroToyShop</subtitle><primaryCategory><categoryId>75708</categoryId><categoryName>TV, Movie &amp; Video Games</categoryName></primaryCategory><galleryURL>http://thumbs2.ebaystatic.com/m/mOMoK_EONx8IWfKaPzSe0Hw/140.jpg</galleryURL><viewItemURL>http://www.ebay.com/itm/Star-Wars-Black-Series-Luke-Skywalker-Figure-Hasbro-/321573499601</viewItemURL><paymentMethod>PayPal</paymentMethod><autoPay>true</autoPay><location>USA</location><country>US</country><shippingInfo><shippingServiceCost currencyId="USD">0.0</shippingServiceCost><shippingType>Free</shippingType><shipToLocations>US</shipToLocations><expeditedShipping>true</expeditedShipping><oneDayShippingAvailable>true</oneDayShippingAvailable><handlingTime>2</handlingTime></shippingInfo><sellingStatus><currentPrice currencyId="USD">9.99</currentPrice><convertedCurrentPrice currencyId="USD">9.99</convertedCurrentPrice><sellingState>Active</sellingState><timeLeft>P23DT16H36M9S</timeLeft></sellingStatus><listingInfo><bestOfferEnabled>false</bestOfferEnabled><buyItNowAvailable>false</buyItNowAvailable><startTime>2014-11-04T21:35:16.000Z</startTime><endTime>2016-01-28T21:40:16.000Z</endTime><listingType>FixedPrice</listingType><gift>false</gift></listingInfo><returnsAccepted>true</returnsAccepted><condition><conditionId>1000</conditionId><conditionDisplayName>New</conditionDisplayName></condition><isMultiVariationListing>false</isMultiVariationListing><topRatedListing>false</topRatedListing></item><item><itemId>281901105693</itemId><title>Star Wars: The Complete Saga (Blu-ray Disc, 2011, 9-Disc Set, Boxed Set) SEALED</title><globalId>EBAY-US</globalId><primaryCategory><categoryId>617</categoryId><categoryName>DVDs &amp; Blu-ray Discs</categoryName></primaryCategory><galleryURL>http://thumbs2.ebaystatic.com/m/mM1Q2ntOxBYi53GrqFpc1Gw/140.jpg</galleryURL><viewItemURL>http://www.ebay.com/itm/Star-Wars-Complete-Saga-Blu-ray-Disc-2011-9-Disc-Set-Boxed-Set-SEALED-/281901105693</viewItemURL><productId type="ReferenceID">98132945</productId><paymentMethod>PayPal</paymentMethod><autoPay>false</autoPay><postalCode>07950</postalCode><location>Morris Plains,NJ,USA</location><country>US</country><shippingInfo><shippingServiceCost currencyId="USD">5.5</shippingServiceCost><shippingType>Flat</shippingType><shipToLocations>US</shipToLocations><expeditedShipping>false</expeditedShipping><oneDayShippingAvailable>false</oneDayShippingAvailable><handlingTime>2</handlingTime></shippingInfo><sellingStatus><currentPrice currencyId="USD">80.99</currentPrice><convertedCurrentPrice currencyId="USD">80.99</convertedCurrentPrice><sellingState>Active</sellingState><timeLeft>P2DT14H1M20S</timeLeft></sellingStatus><listingInfo><bestOfferEnabled>false</bestOfferEnabled><buyItNowAvailable>false</buyItNowAvailable><startTime>2016-01-04T19:05:27.000Z</startTime><endTime>2016-01-07T19:05:27.000Z</endTime><listingType>FixedPrice</listingType><gift>false</gift></listingInfo><returnsAccepted>true</returnsAccepted><condition><conditionId>1000</conditionId><conditionDisplayName>Brand New</conditionDisplayName></condition><isMultiVariationListing>false</isMultiVariationListing><topRatedListing>false</topRatedListing></item><item><itemId>191771273744</itemId><title>Star Wars: The Complete Saga ( 9 Disc Blu-ray Set ) with Slipcover 2015</title><globalId>EBAY-ENCA</globalId><primaryCategory><categoryId>617</categoryId><categoryName>DVDs &amp; Blu-ray Discs</categoryName></primaryCategory><galleryURL>http://thumbs1.ebaystatic.com/m/mYksC4KRs_EXw4FHBifCO_Q/140.jpg</galleryURL><viewItemURL>http://www.ebay.com/itm/Star-Wars-Complete-Saga-9-Disc-Blu-ray-Set-Slipcover-2015-/191771273744</viewItemURL><paymentMethod>PayPal</paymentMethod><autoPay>false</autoPay><location>Canada</location><country>CA</country><shippingInfo><shippingServiceCost currencyId="USD">17.5</shippingServiceCost><shippingType>Flat</shippingType><shipToLocations>US</shipToLocations><shipToLocations>CA</shipToLocations><expeditedShipping>false</expeditedShipping><oneDayShippingAvailable>false</oneDayShippingAvailable><handlingTime>1</handlingTime></shippingInfo><sellingStatus><currentPrice currencyId="USD">63.0</currentPrice><convertedCurrentPrice currencyId="USD">63.0</convertedCurrentPrice><bidCount>18</bidCount><sellingState>Active</sellingState><timeLeft>P0DT0H3M13S</timeLeft></sellingStatus><listingInfo><bestOfferEnabled>false</bestOfferEnabled><buyItNowAvailable>false</buyItNowAvailable><startTime>2015-12-31T05:07:20.000Z</startTime><endTime>2016-01-05T05:07:20.000Z</endTime><listingType>Auction</listingType><gift>false</gift></listingInfo><returnsAccepted>true</returnsAccepted><condition><conditionId>1000</conditionId><conditionDisplayName>Brand New</conditionDisplayName></condition><isMultiVariationListing>false</isMultiVariationListing><topRatedListing>false</topRatedListing></item><item><itemId>262224819563</itemId><title>Star Wars The Complete Saga Blu Ray Disc 2011 9 Disc Set Boxed Set NEW</title><globalId>EBAY-US</globalId><primaryCategory><categoryId>617</categoryId><categoryName>DVDs &amp; Blu-ray Discs</categoryName></primaryCategory><galleryURL>http://thumbs4.ebaystatic.com/m/mpokX8W8akkaxHv6DJED5Jw/140.jpg</galleryURL><viewItemURL>http://www.ebay.com/itm/Star-Wars-Complete-Saga-Blu-Ray-Disc-2011-9-Disc-Set-Boxed-Set-NEW-/262224819563</viewItemURL><productId type="ReferenceID">98132945</productId><paymentMethod>PayPal</paymentMethod><autoPay>true</autoPay><postalCode>06053</postalCode><location>New Britain,CT,USA</location><country>US</country><shippingInfo><shippingServiceCost currencyId="USD">0.0</shippingServiceCost><shippingType>FlatDomesticCalculatedInternational</shippingType><shipToLocations>US</shipToLocations><shipToLocations>CA</shipToLocations><shipToLocations>GB</shipToLocations><shipToLocations>AU</shipToLocations><shipToLocations>AT</shipToLocations><shipToLocations>BE</shipToLocations><shipToLocations>FR</shipToLocations><shipToLocations>DE</shipToLocations><shipToLocations>IT</shipToLocations><shipToLocations>JP</shipToLocations><shipToLocations>ES</shipToLocations><shipToLocations>TW</shipToLocations><shipToLocations>NL</shipToLocations><shipToLocations>CN</shipToLocations><shipToLocations>HK</shipToLocations><shipToLocations>MX</shipToLocations><shipToLocations>DK</shipToLocations><shipToLocations>RO</shipToLocations><shipToLocations>SK</shipToLocations><shipToLocations>BG</shipToLocations><shipToLocations>CZ</shipToLocations><shipToLocations>FI</shipToLocations><shipToLocations>HU</shipToLocations><shipToLocations>LV</shipToLocations><shipToLocations>LT</shipToLocations><shipToLocations>MT</shipToLocations><shipToLocations>EE</shipToLocations><shipToLocations>GR</shipToLocations><shipToLocations>PT</shipToLocations><shipToLocations>CY</shipToLocations><shipToLocations>SI</shipToLocations><shipToLocations>SE</shipToLocations><shipToLocations>KR</shipToLocations><shipToLocations>ID</shipToLocations><shipToLocations>ZA</shipToLocations><shipToLocations>TH</shipToLocations><shipToLocations>IE</shipToLocations><shipToLocations>PL</shipToLocations><shipToLocations>RU</shipToLocations><shipToLocations>IL</shipToLocations><expeditedShipping>false</expeditedShipping><oneDayShippingAvailable>false</oneDayShippingAvailable><handlingTime>1</handlingTime></shippingInfo><sellingStatus><currentPrice currencyId="USD">79.99</currentPrice><convertedCurrentPrice currencyId="USD">79.99</convertedCurrentPrice><sellingState>Active</sellingState><timeLeft>P6DT23H8M24S</timeLeft></sellingStatus><listingInfo><bestOfferEnabled>true</bestOfferEnabled><buyItNowAvailable>false</buyItNowAvailable><startTime>2016-01-05T04:12:31.000Z</startTime><endTime>2016-01-12T04:12:31.000Z</endTime><listingType>FixedPrice</listingType><gift>false</gift></listingInfo><returnsAccepted>false</returnsAccepted><condition><conditionId>1000</conditionId><conditionDisplayName>Brand New</conditionDisplayName></condition><isMultiVariationListing>false</isMultiVariationListing><topRatedListing>false</topRatedListing></item><item><itemId>191771273684</itemId><title>Star Wars: The Complete Saga ( 9 Disc Blu-ray Set ) with Slipcover </title><globalId>EBAY-ENCA</globalId><primaryCategory><categoryId>617</categoryId><categoryName>DVDs &amp; Blu-ray Discs</categoryName></primaryCategory><galleryURL>http://thumbs1.ebaystatic.com/m/mYksC4KRs_EXw4FHBifCO_Q/140.jpg</galleryURL><viewItemURL>http://www.ebay.com/itm/Star-Wars-Complete-Saga-9-Disc-Blu-ray-Set-Slipcover-/191771273684</viewItemURL><paymentMethod>PayPal</paymentMethod><autoPay>false</autoPay><location>Canada</location><country>CA</country><shippingInfo><shippingServiceCost currencyId="USD">17.5</shippingServiceCost><shippingType>Flat</shippingType><shipToLocations>US</shipToLocations><shipToLocations>CA</shipToLocations><expeditedShipping>false</expeditedShipping><oneDayShippingAvailable>false</oneDayShippingAvailable><handlingTime>1</handlingTime></shippingInfo><sellingStatus><currentPrice currencyId="USD">62.0</currentPrice><convertedCurrentPrice currencyId="USD">62.0</convertedCurrentPrice><bidCount>43</bidCount><sellingState>Active</sellingState><timeLeft>P0DT0H2M52S</timeLeft></sellingStatus><listingInfo><bestOfferEnabled>false</bestOfferEnabled><buyItNowAvailable>false</buyItNowAvailable><startTime>2015-12-31T05:06:59.000Z</startTime><endTime>2016-01-05T05:06:59.000Z</endTime><listingType>Auction</listingType><gift>false</gift></listingInfo><returnsAccepted>true</returnsAccepted><condition><conditionId>1000</conditionId><conditionDisplayName>Brand New</conditionDisplayName></condition><isMultiVariationListing>false</isMultiVariationListing><topRatedListing>false</topRatedListing></item><item><itemId>221986245277</itemId><title>Star Wars The Force Awakens Black Series 6" Clone Commander Cody 14 Hasbro NEW</title><globalId>EBAY-US</globalId><primaryCategory><categoryId>75708</categoryId><categoryName>TV, Movie &amp; Video Games</categoryName></primaryCategory><galleryURL>http://thumbs2.ebaystatic.com/m/mPEtBX3GnGuppJHHEJ59sQA/140.jpg</galleryURL><viewItemURL>http://www.ebay.com/itm/Star-Wars-Force-Awakens-Black-Series-6-Clone-Commander-Cody-14-Hasbro-NEW-/221986245277</viewItemURL><paymentMethod>PayPal</paymentMethod><autoPay>false</autoPay><postalCode>21921</postalCode><location>Elkton,MD,USA</location><country>US</country><shippingInfo><shippingServiceCost currencyId="USD">0.0</shippingServiceCost><shippingType>Free</shippingType><shipToLocations>US</shipToLocations><expeditedShipping>true</expeditedShipping><oneDayShippingAvailable>false</oneDayShippingAvailable><handlingTime>1</handlingTime></shippingInfo><sellingStatus><currentPrice currencyId="USD">21.95</currentPrice><convertedCurrentPrice currencyId="USD">21.95</convertedCurrentPrice><sellingState>Active</sellingState><timeLeft>P6DT20H41M52S</timeLeft></sellingStatus><listingInfo><bestOfferEnabled>false</bestOfferEnabled><buyItNowAvailable>false</buyItNowAvailable><startTime>2016-01-05T01:45:59.000Z</startTime><endTime>2016-01-12T01:45:59.000Z</endTime><listingType>StoreInventory</listingType><gift>false</gift></listingInfo><returnsAccepted>true</returnsAccepted><condition><conditionId>1000</conditionId><conditionDisplayName>New</conditionDisplayName></condition><isMultiVariationListing>false</isMultiVariationListing><topRatedListing>false</topRatedListing></item><item><itemId>321789480281</itemId><title>Star Wars The Black Series Clone Commander Doom Figure by Hasbro</title><globalId>EBAY-US</globalId><subtitle>Buy direct from HasbroToyShop</subtitle><primaryCategory><categoryId>75708</categoryId><categoryName>TV, Movie &amp; Video Games</categoryName></primaryCategory><galleryURL>http://thumbs2.ebaystatic.com/m/mO0YePfqzGlg_NQHKF8kOFQ/140.jpg</galleryURL><viewItemURL>http://www.ebay.com/itm/Star-Wars-Black-Series-Clone-Commander-Doom-Figure-Hasbro-/321789480281</viewItemURL><paymentMethod>PayPal</paymentMethod><autoPay>true</autoPay><location>USA</location><country>US</country><shippingInfo><shippingServiceCost currencyId="USD">0.0</shippingServiceCost><shippingType>Free</shippingType><shipToLocations>US</shipToLocations><expeditedShipping>true</expeditedShipping><oneDayShippingAvailable>true</oneDayShippingAvailable><handlingTime>2</handlingTime></shippingInfo><sellingStatus><currentPrice currencyId="USD">12.99</currentPrice><convertedCurrentPrice currencyId="USD">12.99</convertedCurrentPrice><sellingState>Active</sellingState><timeLeft>P13DT14H8M15S</timeLeft></sellingStatus><listingInfo><bestOfferEnabled>false</bestOfferEnabled><buyItNowAvailable>false</buyItNowAvailable><startTime>2015-06-22T19:07:22.000Z</startTime><endTime>2016-01-18T19:12:22.000Z</endTime><listingType>FixedPrice</listingType><gift>false</gift></listingInfo><returnsAccepted>true</returnsAccepted><condition><conditionId>1000</conditionId><conditionDisplayName>New</conditionDisplayName></condition><isMultiVariationListing>false</isMultiVariationListing><topRatedListing>false</topRatedListing></item></searchResult><paginationOutput><pageNumber>1</pageNumber><entriesPerPage>10</entriesPerPage><totalPages>96139</totalPages><totalEntries>961382</totalEntries></paginationOutput><itemSearchURL>http://www.ebay.com/sch/i.html?_nkw=star+wars&amp;_ddo=1&amp;_ipg=10&amp;_pgn=1</itemSearchURL></findItemsByKeywordsResponse>